datawrappergraphics/__init__.py
datawrappergraphics/errors.py
datawrappergraphics/graphics.py
datawrappergraphics/icons.py
datawrappergraphics-0.3.38.dist-info/METADATA
datawrappergraphics-0.3.38.dist-info/WHEEL
datawrappergraphics-0.3.38.dist-info/top_level.txt
datawrappergraphics-0.3.38.dist-info/RECORD
