Metadata-Version: 2.1
Name: datawrappergraphics
Version: 0.3.38
Summary: A package for interacting with Datawrapper maps, charts, and folders.
Home-page: https://github.com/dexmcmillan/datawrappergraphics
Author: Dexter McMillan
License: MIT
